[
   {
        "year": 2021,
        "round": "A",
        "number": 1,
        "title": "K-Goodness String",
        "solvedTest2": 13336,
        "solvedTest1": 40,
        "didNotSolve": 6215,
        "totalSubmitters": 19850,
        "url": "https://codingcompetitions.withgoogle.com/kickstart/round/0000000000436140/000000000068cca3"
    },
    {
        "year": 2021,
        "round": "A",
        "number": 2,
        "title": "L Shaped Plots",
        "solvedTest2": 4869,
        "solvedTest1": 584,
        "didNotSolve": 2473,
        "totalSubmitters": 19850,
        "url": "https://codingcompetitions.withgoogle.com/kickstart/round/0000000000436140/000000000068c509"
    },
    {
        "year": 2021,
        "round": "A",
        "number": 3,
        "title": "Rabbit House",
        "solvedTest2": 2807,
        "solvedTest1": 445,
        "didNotSolve": 3749,
        "totalSubmitters": 19850,
        "url": "https://codingcompetitions.withgoogle.com/kickstart/round/0000000000436140/000000000068cb14"
    },
    {
        "year": 2021,
        "round": "A",
        "number": 4,
        "title": "Checksum",
        "solvedTest3": 116,
        "solvedTest2": 8,
        "solvedTest1": 438,
        "didNotSolve": 1733,
        "totalSubmitters": 19850,
        "url": "https://codingcompetitions.withgoogle.com/kickstart/round/0000000000436140/000000000068c2c3"
    },
    {
        "year": 2020,
        "round": "H",
        "number": 1,
        "title": "Retype",
        "solvedTest2": 4071,
        "solvedTest1": 192,
        "didNotSolve": 338,
        "totalSubmitters": 4700,
        "url": "https://codingcompetitions.withgoogle.com/kickstart/round/000000000019ff49/000000000043adc7"
    },
    {
        "year": 2020,
        "round": "H",
        "number": 2,
        "title": "Boring Numbers",
        "solvedTest2": 805,
        "solvedTest1": 2139,
        "didNotSolve": 474,
        "totalSubmitters": 4700,
        "url": "https://codingcompetitions.withgoogle.com/kickstart/round/000000000019ff49/000000000043b0c6"
    },
    {
        "year": 2020,
        "round": "H",
        "number": 3,
        "title": "Rugby",
        "solvedTest2": 320,
        "solvedTest1": 328,
        "didNotSolve": 598,
        "totalSubmitters": 4700,
        "url": "https://codingcompetitions.withgoogle.com/kickstart/round/000000000019ff49/000000000043b027"
    },
    {
        "year": 2020,
        "round": "H",
        "number": 4,
        "title": "Friends",
        "solvedTest2": 626,
        "solvedTest1": 461,
        "didNotSolve": 382,
        "totalSubmitters": 4700,
        "url": "https://codingcompetitions.withgoogle.com/kickstart/round/000000000019ff49/000000000043aee7"
    },
    {
        "year": 2020,
        "round": "G",
        "number": 1,
        "title": "Kick_Start",
        "solvedTest2": 5780,
        "solvedTest1": 531,
        "didNotSolve": 1495,
        "totalSubmitters": 8100,
        "url": "https://codingcompetitions.withgoogle.com/kickstart/round/00000000001a0069/0000000000414bfb"
    },
    {
        "year": 2020,
        "round": "G",
        "number": 2,
        "title": "Maximum Coins",
        "solvedTest2": 5590,
        "solvedTest1": 425,
        "didNotSolve": 454,
        "totalSubmitters": 8100,
        "url": "https://codingcompetitions.withgoogle.com/kickstart/round/00000000001a0069/0000000000414a23"
    },
    {
        "year": 2020,
        "round": "G",
        "number": 3,
        "title": "Combination Lock",
        "solvedTest3": 606,
        "solvedTest2": 1474,
        "solvedTest1": 1625,
        "didNotSolve": 1096,
        "totalSubmitters": 8100,
        "url": "https://codingcompetitions.withgoogle.com/kickstart/round/00000000001a0069/0000000000414a24"
    },
    {
        "year": 2020,
        "round": "G",
        "number": 4,
        "title": "Merge Cards",
        "solvedTest3": 248,
        "solvedTest2": 105,
        "solvedTest1": 699,
        "didNotSolve": 307,
        "totalSubmitters": 8100,
        "url": "https://codingcompetitions.withgoogle.com/kickstart/round/00000000001a0069/0000000000415054"
    },
    {
        "year": 2020,
        "round": "F",
        "number": 1,
        "title": "ATM Queue",
        "solvedTest2": 3509,
        "solvedTest1": 1590,
        "didNotSolve": 1065,
        "totalSubmitters": 6200,
        "url": "https://codingcompetitions.withgoogle.com/kickstart/round/000000000019ff48/00000000003f4ed8"
    },
    {
        "year": 2020,
        "round": "F",
        "number": 2,
        "title": "Metal Harvest",
        "solvedTest2": 2448,
        "solvedTest1": 233,
        "didNotSolve": 1249,
        "totalSubmitters": 6200,
        "url": "https://codingcompetitions.withgoogle.com/kickstart/round/000000000019ff48/00000000003f4b8b"
    },
    {
        "year": 2020,
        "round": "F",
        "number": 3,
        "title": "Painters' Duel",
        "solvedTest2": 346,
        "solvedTest1": 1151,
        "didNotSolve": 297,
        "totalSubmitters": 6200,
        "url": "https://codingcompetitions.withgoogle.com/kickstart/round/000000000019ff48/00000000003f47fb"
    },
    {
        "year": 2020,
        "round": "F",
        "number": 4,
        "title": "Yeetzhee",
        "solvedTest2": 69,
        "solvedTest1": 25,
        "didNotSolve": 115,
        "totalSubmitters": 6200,
        "url": "https://codingcompetitions.withgoogle.com/kickstart/round/000000000019ff48/00000000003f4dea"
    },
    {
        "year": 2020,
        "round": "E",
        "number": 1,
        "title": "Longest Arithmetic",
        "solvedTest2": 8888,
        "solvedTest1": 270,
        "didNotSolve": 2111,
        "totalSubmitters": 11401,
        "url": "https://codingcompetitions.withgoogle.com/kickstart/round/000000000019ff47/00000000003bf4ed"
    },
    {
        "year": 2020,
        "round": "E",
        "number": 2,
        "title": "High Buildings",
        "solvedTest2": 2345,
        "solvedTest1": 352,
        "didNotSolve": 3138,
        "totalSubmitters": 11401,
        "url": "https://codingcompetitions.withgoogle.com/kickstart/round/000000000019ff47/00000000003bef73"
    },
    {
        "year": 2020,
        "round": "E",
        "number": 3,
        "title": "Toys",
        "solvedTest2": 288,
        "solvedTest1": 756,
        "didNotSolve": 977,
        "totalSubmitters": 11401,
        "url": "https://codingcompetitions.withgoogle.com/kickstart/round/000000000019ff47/00000000003bede9"
    },
    {
        "year": 2020,
        "round": "E",
        "number": 4,
        "title": "Golden Stone",
        "solvedTest2": 77,
        "solvedTest1": 36,
        "didNotSolve": 132,
        "totalSubmitters": 11401,
        "url": "https://codingcompetitions.withgoogle.com/kickstart/round/000000000019ff47/00000000003bef29"
    },
    {
        "year": 2020,
        "round": "D",
        "number": 1,
        "title": "Record Breaker",
        "solvedTest2": 7799,
        "solvedTest1": 343,
        "didNotSolve": 3469,
        "totalSubmitters": 11704,
        "url": "https://codingcompetitions.withgoogle.com/kickstart/round/000000000019ff08/0000000000387171"
    },
    {
        "year": 2020,
        "round": "D",
        "number": 2,
        "title": "Alien Piano",
        "solvedTest2": 3929,
        "solvedTest1": 661,
        "didNotSolve": 2228,
        "totalSubmitters": 11704,
        "url": "https://codingcompetitions.withgoogle.com/kickstart/round/000000000019ff08/0000000000387174"
    },
    {
        "year": 2020,
        "round": "D",
        "number": 3,
        "title": "Beauty of tree",
        "solvedTest2": 602,
        "solvedTest1": 1040,
        "didNotSolve": 590,
        "totalSubmitters": 11704,
        "url": "https://codingcompetitions.withgoogle.com/kickstart/round/000000000019ff08/0000000000386edd"
    },
    {
        "year": 2020,
        "round": "D",
        "number": 4,
        "title": "Locked Doors",
        "solvedTest2": 112,
        "solvedTest1": 1958,
        "didNotSolve": 484,
        "totalSubmitters": 11704,
        "url": "https://codingcompetitions.withgoogle.com/kickstart/round/000000000019ff08/0000000000386d5c"
    },
    {
        "year": 2020,
        "round": "C",
        "number": 1,
        "title": "Countdown",
        "solvedTest2": 9017,
        "solvedTest1": 808,
        "didNotSolve": 3594,
        "totalSubmitters": 13650,
        "url": "https://codingcompetitions.withgoogle.com/kickstart/round/000000000019ff43/00000000003380d2"
    },
    {
        "year": 2020,
        "round": "C",
        "number": 2,
        "title": "Stable Wall",
        "solvedTest2": 2632,
        "solvedTest1": 173,
        "didNotSolve": 933,
        "totalSubmitters": 13650,
        "url": "https://codingcompetitions.withgoogle.com/kickstart/round/000000000019ff43/00000000003379bb"
    },
    {
        "year": 2020,
        "round": "C",
        "number": 3,
        "title": "Perfect Subarray",
        "solvedTest2": 685,
        "solvedTest1": 5712,
        "didNotSolve": 1965,
        "totalSubmitters": 13650,
        "url": "https://codingcompetitions.withgoogle.com/kickstart/round/000000000019ff43/00000000003381cb"
    },
    {
        "year": 2020,
        "round": "C",
        "number": 4,
        "title": "Candies",
        "solvedTest2": 655,
        "solvedTest1": 159,
        "didNotSolve": 3149,
        "totalSubmitters": 13650,
        "url": "https://codingcompetitions.withgoogle.com/kickstart/round/000000000019ff43/0000000000337b4d"
    },
    {
        "year": 2020,
        "round": "B",
        "number": 1,
        "title": "Bike Tour",
        "solvedTest2": 9267,
        "solvedTest1": 36,
        "didNotSolve": 909,
        "totalSubmitters": 10300,
        "url": "https://codingcompetitions.withgoogle.com/kickstart/round/000000000019ffc8/00000000002d82e6"
    },
    {
        "year": 2020,
        "round": "B",
        "number": 2,
        "title": "Bus Routes",
        "solvedTest2": 5811,
        "solvedTest1": 1143,
        "didNotSolve": 1233,
        "totalSubmitters": 10300,
        "url": "https://codingcompetitions.withgoogle.com/kickstart/round/000000000019ffc8/00000000002d83bf"
    },
    {
        "year": 2020,
        "round": "B",
        "number": 3,
        "title": "Robot Path Decoding",
        "solvedTest2": 2733,
        "solvedTest1": 2019,
        "didNotSolve": 678,
        "totalSubmitters": 10300,
        "url": "https://codingcompetitions.withgoogle.com/kickstart/round/000000000019ffc8/00000000002d83dc"
    },
    {
        "year": 2020,
        "round": "B",
        "number": 4,
        "title": "Wandering Robot",
        "solvedTest2": 135,
        "solvedTest1": 1616,
        "didNotSolve": 737,
        "totalSubmitters": 10300,
        "url": "https://codingcompetitions.withgoogle.com/kickstart/round/000000000019ffc8/00000000002d8565"
    },
    {
        "year": 2020,
        "round": "A",
        "number": 1,
        "title": "Allocation",
        "solvedTest2": 10276,
        "solvedTest1": 576,
        "didNotSolve": 2750,
        "totalSubmitters": 13700,
        "url": "https://codingcompetitions.withgoogle.com/kickstart/round/000000000019ffc7/00000000001d3f56"
    },
    {
        "year": 2020,
        "round": "A",
        "number": 2,
        "title": "Plates",
        "solvedTest2": 2941,
        "solvedTest1": 1114,
        "didNotSolve": 2075,
        "totalSubmitters": 13700,
        "url": "https://codingcompetitions.withgoogle.com/kickstart/round/000000000019ffc7/00000000001d40bb"
    },
    {
        "year": 2020,
        "round": "A",
        "number": 3,
        "title": "Workout",
        "solvedTest2": 1925,
        "solvedTest1": 3326,
        "didNotSolve": 1074,
        "totalSubmitters": 13700,
        "url": "https://codingcompetitions.withgoogle.com/kickstart/round/000000000019ffc7/00000000001d3f5b"
    },
    {
        "year": 2020,
        "round": "A",
        "number": 4,
        "title": "Bundling",
        "solvedTest2": 1032,
        "solvedTest1": 119,
        "didNotSolve": 1511,
        "totalSubmitters": 13700,
        "url": "https://codingcompetitions.withgoogle.com/kickstart/round/000000000019ffc7/00000000001d3ff3"
    },
    {
        "year": 2019,
        "round": "H",
        "number": 1,
        "title": "H-index",
        "solvedTest2": 877,
        "solvedTest1": 1207,
        "didNotSolve": 1028,
        "totalSubmitters": 3350,
        "url": "https://codingcompetitions.withgoogle.com/kickstart/round/0000000000050edd/00000000001a274e"
    },
    {
        "year": 2019,
        "round": "H",
        "number": 2,
        "title": "Diagonal Puzzle",
        "solvedTest2": 124,
        "solvedTest1": 57,
        "didNotSolve": 498,
        "totalSubmitters": 3350,
        "url": "https://codingcompetitions.withgoogle.com/kickstart/round/0000000000050edd/00000000001a2835"
    },
    {
        "year": 2019,
        "round": "H",
        "number": 3,
        "title": "Elevanagram",
        "solvedTest2": 184,
        "solvedTest1": 335,
        "didNotSolve": 750,
        "totalSubmitters": 3350,
        "url": "https://codingcompetitions.withgoogle.com/kickstart/round/0000000000050edd/00000000001a286d"
    },
    {
        "year": 2019,
        "round": "G",
        "number": 1,
        "title": "Book Reading",
        "solvedTest2": 1067,
        "solvedTest1": 2278,
        "didNotSolve": 1662,
        "totalSubmitters": 5250,
        "url": "https://codingcompetitions.withgoogle.com/kickstart/round/0000000000050e02/000000000018fd0d"
    },
    {
        "year": 2019,
        "round": "G",
        "number": 2,
        "title": "The Equation",
        "solvedTest2": 569,
        "solvedTest1": 1048,
        "didNotSolve": 1141,
        "totalSubmitters": 5250,
        "url": "https://codingcompetitions.withgoogle.com/kickstart/round/0000000000050e02/000000000018fe36"
    },
    {
        "year": 2019,
        "round": "G",
        "number": 3,
        "title": "Shifts",
        "solvedTest2": 291,
        "solvedTest1": 875,
        "didNotSolve": 873,
        "totalSubmitters": 5250,
        "url": "https://codingcompetitions.withgoogle.com/kickstart/round/0000000000050e02/000000000018fd5e"
    },
    {
        "year": 2019,
        "round": "F",
        "number": 1,
        "title": "Flattening",
        "solvedTest2": 320,
        "solvedTest1": 67,
        "didNotSolve": 1948,
        "totalSubmitters": 3350,
        "url": "https://codingcompetitions.withgoogle.com/kickstart/round/0000000000050edc/000000000018666c"
    },
    {
        "year": 2019,
        "round": "F",
        "number": 2,
        "title": "Teach Me",
        "solvedTest2": 179,
        "solvedTest1": 1160,
        "didNotSolve": 679,
        "totalSubmitters": 3350,
        "url": "https://codingcompetitions.withgoogle.com/kickstart/round/0000000000050edc/00000000001864bc"
    },
    {
        "year": 2019,
        "round": "F",
        "number": 3,
        "title": "Spectating Villages",
        "solvedTest2": 143,
        "solvedTest1": 305,
        "didNotSolve": 591,
        "totalSubmitters": 3350,
        "url": "https://codingcompetitions.withgoogle.com/kickstart/round/0000000000050edc/000000000018666b"
    },
    {
        "year": 2019,
        "round": "E",
        "number": 1,
        "title": "Cherries Mesh",
        "solvedTest2": 1570,
        "solvedTest1": 802,
        "didNotSolve": 2823,
        "totalSubmitters": 6350,
        "url": "https://codingcompetitions.withgoogle.com/kickstart/round/0000000000050edb/0000000000170721"
    },
    {
        "year": 2019,
        "round": "E",
        "number": 2,
        "title": "Code-Eat Switcher",
        "solvedTest2": 249,
        "solvedTest1": 371,
        "didNotSolve": 1387,
        "totalSubmitters": 6350,
        "url": "https://codingcompetitions.withgoogle.com/kickstart/round/0000000000050edb/00000000001707b8"
    },
    {
        "year": 2019,
        "round": "E",
        "number": 3,
        "title": "Street Checkers",
        "solvedTest2": 435,
        "solvedTest1": 995,
        "didNotSolve": 2021,
        "totalSubmitters": 6350,
        "url": "https://codingcompetitions.withgoogle.com/kickstart/round/0000000000050edb/00000000001707b9"
    },
    {
        "year": 2019,
        "round": "D",
        "number": 1,
        "title": "X or What?",
        "solvedTest2": 450,
        "solvedTest1": 1199,
        "didNotSolve": 2098,
        "totalSubmitters": 4400,
        "url": "https://codingcompetitions.withgoogle.com/kickstart/round/0000000000051061/0000000000161426"
    },
    {
        "year": 2019,
        "round": "D",
        "number": 2,
        "title": "Latest Guests",
        "solvedTest2": 110,
        "solvedTest1": 790,
        "didNotSolve": 773,
        "totalSubmitters": 4400,
        "url": "https://codingcompetitions.withgoogle.com/kickstart/round/0000000000051061/0000000000161427"
    },
    {
        "year": 2019,
        "round": "D",
        "number": 3,
        "title": "Food Stalls",
        "solvedTest2": 52,
        "solvedTest1": 743,
        "didNotSolve": 950,
        "totalSubmitters": 4400,
        "url": "https://codingcompetitions.withgoogle.com/kickstart/round/0000000000051061/0000000000161476"
    },
    {
        "year": 2019,
        "round": "C",
        "number": 1,
        "title": "Wiggle Walk",
        "solvedTest2": 569,
        "solvedTest1": 1433,
        "didNotSolve": 1029,
        "totalSubmitters": 3100,
        "url": "https://codingcompetitions.withgoogle.com/kickstart/round/0000000000050ff2/0000000000150aac"
    },
    {
        "year": 2019,
        "round": "C",
        "number": 2,
        "title": "Circuit Board",
        "solvedTest2": 553,
        "solvedTest1": 221,
        "didNotSolve": 468,
        "totalSubmitters": 3100,
        "url": "https://codingcompetitions.withgoogle.com/kickstart/round/0000000000050ff2/0000000000150aae"
    },
    {
        "year": 2019,
        "round": "C",
        "number": 3,
        "title": "Catch Some",
        "solvedTest2": 161,
        "solvedTest1": 66,
        "didNotSolve": 255,
        "totalSubmitters": 3100,
        "url": "https://codingcompetitions.withgoogle.com/kickstart/round/0000000000050ff2/0000000000150a0d"
    },
    {
        "year": 2019,
        "round": "B",
        "number": 1,
        "title": "Building Palindromes",
        "solvedTest2": 1011,
        "solvedTest1": 1237,
        "didNotSolve": 315,
        "totalSubmitters": 2650,
        "url": "https://codingcompetitions.withgoogle.com/kickstart/round/0000000000050e01/00000000000698d6"
    },
    {
        "year": 2019,
        "round": "B",
        "number": 2,
        "title": "Energy Stones",
        "solvedTest2": 65,
        "solvedTest1": 58,
        "didNotSolve": 1127,
        "totalSubmitters": 2650,
        "url": "https://codingcompetitions.withgoogle.com/kickstart/round/0000000000050e01/000000000006987d"
    },
    {
        "year": 2019,
        "round": "B",
        "number": 3,
        "title": "Diverse Subarray",
        "solvedTest2": 81,
        "solvedTest1": 619,
        "didNotSolve": 442,
        "totalSubmitters": 2650,
        "url": "https://codingcompetitions.withgoogle.com/kickstart/round/0000000000050e01/0000000000069881"
    },
    {
        "year": 2019,
        "round": "A",
        "number": 1,
        "title": "Training",
        "solvedTest2": 2112,
        "solvedTest1": 1168,
        "didNotSolve": 1337,
        "totalSubmitters": 4900,
        "url": "https://codingcompetitions.withgoogle.com/kickstart/round/0000000000050e01/00000000000698d6"
    },
    {
        "year": 2019,
        "round": "A",
        "number": 2,
        "title": "Parcels",
        "solvedTest2": 137,
        "solvedTest1": 1009,
        "didNotSolve": 848,
        "totalSubmitters": 4900,
        "url": "https://codingcompetitions.withgoogle.com/kickstart/round/0000000000050e01/000000000006987d"
    },
    {
        "year": 2019,
        "round": "A",
        "number": 3,
        "title": "Contention",
        "solvedTest2": 2,
        "solvedTest1": 8,
        "didNotSolve": 1031,
        "totalSubmitters": 4900,
        "url": "https://codingcompetitions.withgoogle.com/kickstart/round/0000000000050e01/0000000000069881"
    },
    {
        "year": 2019,
        "round": "Practice",
        "number": 1,
        "title": "Number Guessing",
        "solvedTest2": 1495,
        "solvedTest1": 164,
        "didNotSolve": 695,
        "totalSubmitters": 2500,
        "url": "https://codingcompetitions.withgoogle.com/kickstart/round/0000000000051060/00000000000588f4"
    },
    {
        "year": 2019,
        "round": "Practice",
        "number": 2,
        "title": "Mural",
        "solvedTest2": 875,
        "solvedTest1": 283,
        "didNotSolve": 264,
        "totalSubmitters": 2500,
        "url": "https://codingcompetitions.withgoogle.com/kickstart/round/0000000000051060/0000000000058b89"
    },
    {
        "year": 2019,
        "round": "Practice",
        "number": 3,
        "title": "Kickstart Alarm",
        "solvedTest2": 154,
        "solvedTest1": 417,
        "didNotSolve": 275,
        "totalSubmitters": 2500,
        "url": "https://codingcompetitions.withgoogle.com/kickstart/round/0000000000051060/0000000000058a56"
    },
    {
        "year": 2018,
        "round": "H",
        "number": 1,
        "title": "Big Buttons",
        "solvedTest2": 1476,
        "solvedTest1": 211,
        "didNotSolve": 31,
        "totalSubmitters": 1800,
        "url": "https://codingcompetitions.withgoogle.com/kickstart/round/0000000000050ee2/0000000000051136"
    },
    {
        "year": 2018,
        "round": "H",
        "number": 2,
        "title": "Mural",
        "solvedTest2": 1014,
        "solvedTest1": 324,
        "didNotSolve": 90,
        "totalSubmitters": 1800,
        "url": "https://codingcompetitions.withgoogle.com/kickstart/round/0000000000050ee2/000000000005118a"
    },
    {
        "year": 2018,
        "round": "H",
        "number": 3,
        "title": "Let Me Count The Ways",
        "solvedTest2": 327,
        "solvedTest1": 143,
        "didNotSolve": 187,
        "totalSubmitters": 1800,
        "url": "https://codingcompetitions.withgoogle.com/kickstart/round/0000000000050ee2/0000000000051189"
    },
    {
        "year": 2018,
        "round": "G",
        "number": 1,
        "title": "Product Triplets",
        "solvedTest2": 498,
        "solvedTest1": 1354,
        "didNotSolve": 5,
        "totalSubmitters": 1900,
        "url": "https://codingcompetitions.withgoogle.com/kickstart/round/0000000000051066/0000000000051187"
    },
    {
        "year": 2018,
        "round": "G",
        "number": 2,
        "title": "Combining Classes",
        "solvedTest2": 174,
        "solvedTest1": 143,
        "didNotSolve": 507,
        "totalSubmitters": 1900,
        "url": "https://codingcompetitions.withgoogle.com/kickstart/round/0000000000051066/0000000000051007"
    },
    {
        "year": 2018,
        "round": "G",
        "number": 3,
        "title": "Cave Escape",
        "solvedTest2": 20,
        "solvedTest1": 172,
        "didNotSolve": 128,
        "totalSubmitters": 1900,
        "url": "https://codingcompetitions.withgoogle.com/kickstart/round/0000000000051066/0000000000051135"
    },
    {
        "year": 2018,
        "round": "F",
        "number": 1,
        "title": "Common Anagrams",
        "solvedTest2": 1467,
        "solvedTest1": 74,
        "didNotSolve": 1,
        "totalSubmitters": 1550,
        "url": "https://codingcompetitions.withgoogle.com/kickstart/round/0000000000050e07/00000000000510f2"
    },
    {
        "year": 2018,
        "round": "F",
        "number": 2,
        "title": "Specializing Villages",
        "solvedTest2": 121,
        "solvedTest1": 349,
        "didNotSolve": 135,
        "totalSubmitters": 1550,
        "url": "https://codingcompetitions.withgoogle.com/kickstart/round/0000000000050e07/0000000000051134"
    },
    {
        "year": 2018,
        "round": "F",
        "number": 3,
        "title": "Palindromic Sequence",
        "solvedTest2": 2,
        "solvedTest1": 14,
        "didNotSolve": 227,
        "totalSubmitters": 1550,
        "url": "https://codingcompetitions.withgoogle.com/kickstart/round/0000000000050e07/0000000000051186"
    },
    {
        "year": 2018,
        "round": "E",
        "number": 1,
        "title": "Board Game",
        "solvedTest2": 13,
        "solvedTest1": 262,
        "didNotSolve": 324,
        "totalSubmitters": 2350,
        "url": "https://codingcompetitions.withgoogle.com/kickstart/round/0000000000050ff5/0000000000051184"
    },
    {
        "year": 2018,
        "round": "E",
        "number": 2,
        "title": "Milk Tea",
        "solvedTest2": 465,
        "solvedTest1": 888,
        "didNotSolve": 283,
        "totalSubmitters": 2350,
        "url": "https://codingcompetitions.withgoogle.com/kickstart/round/0000000000050ff5/0000000000051185"
    },
    {
        "year": 2018,
        "round": "E",
        "number": 3,
        "title": "Yogurt",
        "solvedTest2": 2028,
        "solvedTest1": 288,
        "didNotSolve": 11,
        "totalSubmitters": 2350,
        "url": "https://codingcompetitions.withgoogle.com/kickstart/round/0000000000050ff5/00000000000510f1"
    },
    {
        "year": 2018,
        "round": "D",
        "number": 1,
        "title": "Candies",
        "solvedTest2": 180,
        "solvedTest1": 495,
        "didNotSolve": 96,
        "totalSubmitters": 900,
        "url": "https://codingcompetitions.withgoogle.com/kickstart/round/0000000000050ee1/00000000000510ef"
    },
    {
        "year": 2018,
        "round": "D",
        "number": 2,
        "title": "Paragliding",
        "solvedTest2": 262,
        "solvedTest1": 363,
        "didNotSolve": 74,
        "totalSubmitters": 900,
        "url": "https://codingcompetitions.withgoogle.com/kickstart/round/0000000000050ee1/0000000000051006"
    },
    {
        "year": 2018,
        "round": "D",
        "number": 3,
        "title": "Funniest Word Search",
        "solvedTest2": 22,
        "solvedTest1": 113,
        "didNotSolve": 70,
        "totalSubmitters": 900,
        "url": "https://codingcompetitions.withgoogle.com/kickstart/round/0000000000050ee1/00000000000510f0"
    },
    {
        "year": 2018,
        "round": "C",
        "number": 1,
        "title": "Planet Distance",
        "solvedTest2": 569,
        "solvedTest1": 71,
        "didNotSolve": 7,
        "totalSubmitters": 700,
        "url": "https://codingcompetitions.withgoogle.com/kickstart/round/0000000000050ee0/0000000000051005"
    },
    {
        "year": 2018,
        "round": "C",
        "number": 2,
        "title": "Fairies and Witches",
        "solvedTest2": 118,
        "solvedTest1": 125,
        "didNotSolve": 31,
        "totalSubmitters": 700,
        "url": "https://codingcompetitions.withgoogle.com/kickstart/round/0000000000050ee0/0000000000051132"
    },
    {
        "year": 2018,
        "round": "C",
        "number": 3,
        "title": "Kickstart Alarm",
        "solvedTest2": 192,
        "solvedTest1": 200,
        "didNotSolve": 36,
        "totalSubmitters": 700,
        "url": "https://codingcompetitions.withgoogle.com/kickstart/round/0000000000050ee0/0000000000051133"
    },
    {
        "year": 2018,
        "round": "B",
        "number": 1,
        "title": "No Nine",
        "solvedTest2": 177,
        "solvedTest1": 570,
        "didNotSolve": 1,
        "totalSubmitters": 800,
        "url": "https://codingcompetitions.withgoogle.com/kickstart/round/0000000000050ff4/0000000000051183"
    },
    {
        "year": 2018,
        "round": "B",
        "number": 2,
        "title": "Sherlock and the Bit Strings",
        "solvedTest2": 19,
        "solvedTest1": 258,
        "didNotSolve": 144,
        "totalSubmitters": 800,
        "url": "https://codingcompetitions.withgoogle.com/kickstart/round/0000000000050ff4/000000000005107b"
    },
    {
        "year": 2018,
        "round": "B",
        "number": 3,
        "title": "King's Circle",
        "solvedTest2": 14,
        "solvedTest1": 41,
        "didNotSolve": 87,
        "totalSubmitters": 800,
        "url": "https://codingcompetitions.withgoogle.com/kickstart/round/0000000000050ff4/00000000000510ee"
    },
    {
        "year": 2018,
        "round": "A",
        "number": 1,
        "title": "Even Digits",
        "solvedTest2": 775,
        "solvedTest1": 548,
        "didNotSolve": 5,
        "totalSubmitters": 1350,
        "url": "https://codingcompetitions.withgoogle.com/kickstart/round/0000000000050edf/00000000000510ed"
    },
    {
        "year": 2018,
        "round": "A",
        "number": 2,
        "title": "Lucky Dip",
        "solvedTest2": 253,
        "solvedTest1": 131,
        "didNotSolve": 291,
        "totalSubmitters": 1350,
        "url": "https://codingcompetitions.withgoogle.com/kickstart/round/0000000000050edf/0000000000050e1d"
    },
    {
        "year": 2018,
        "round": "A",
        "number": 3,
        "title": "Scrambled Words",
        "solvedTest2": 31,
        "solvedTest1": 215,
        "didNotSolve": 116,
        "totalSubmitters": 1350,
        "url": "https://codingcompetitions.withgoogle.com/kickstart/round/0000000000050edf/0000000000051004"
    },
    {
        "year": 2017,
        "round": "G",
        "number": 1,
        "title": "Huge Numbers",
        "solvedTest2": 46,
        "solvedTest1": 605,
        "didNotSolve": 12,
        "totalSubmitters": 1200,
        "url": "https://codingcompetitions.withgoogle.com/kickstart/round/0000000000201b7d/0000000000201c03"
    },
    {
        "year": 2017,
        "round": "G",
        "number": 2,
        "title": "Cards Game",
        "solvedTest2": 202,
        "solvedTest1": 244,
        "didNotSolve": 165,
        "totalSubmitters": 1200,
        "url": "https://codingcompetitions.withgoogle.com/kickstart/round/0000000000201b7d/0000000000201c9c"
    },
    {
        "year": 2017,
        "round": "G",
        "number": 3,
        "title": "Matrix Cutting",
        "solvedTest2": 226,
        "solvedTest1": 257,
        "didNotSolve": 55,
        "totalSubmitters": 1200,
        "url": "https://codingcompetitions.withgoogle.com/kickstart/round/0000000000201b7d/0000000000201d2b"
    },
    {
        "year": 2017,
        "round": "F",
        "number": 1,
        "title": "Cake",
        "solvedTest2": 1122,
        "solvedTest1": 131,
        "didNotSolve": 168,
        "totalSubmitters": 1750,
        "url": "https://codingcompetitions.withgoogle.com/kickstart/round/0000000000201d29/0000000000201d2a"
    },
    {
        "year": 2017,
        "round": "F",
        "number": 2,
        "title": "Kicksort",
        "solvedTest2": 975,
        "solvedTest1": 470,
        "didNotSolve": 38,
        "totalSubmitters": 1750,
        "url": "https://codingcompetitions.withgoogle.com/kickstart/round/0000000000201d29/0000000000201b7c"
    },
    {
        "year": 2017,
        "round": "F",
        "number": 3,
        "title": "Dance Battle",
        "solvedTest2": 831,
        "solvedTest1": 135,
        "didNotSolve": 217,
        "totalSubmitters": 1750,
        "url": "https://codingcompetitions.withgoogle.com/kickstart/round/0000000000201d29/0000000000201c02"
    },
    {
        "year": 2017,
        "round": "F",
        "number": 4,
        "title": "Catch Them All",
        "solvedTest2": 218,
        "solvedTest1": 214,
        "didNotSolve": 196,
        "totalSubmitters": 1750,
        "url": "https://codingcompetitions.withgoogle.com/kickstart/round/0000000000201d29/0000000000201c9b"
    },
    {
        "year": 2017,
        "round": "E",
        "number": 1,
        "title": "Trapezoid Counting",
        "solvedTest2": 347,
        "solvedTest1": 213,
        "didNotSolve": 76,
        "totalSubmitters": 1500,
        "url": "https://codingcompetitions.withgoogle.com/kickstart/round/0000000000201bfe/0000000000201d24"
    },
    {
        "year": 2017,
        "round": "E",
        "number": 2,
        "title": "Copy & Paste",
        "solvedTest2": 213,
        "solvedTest1": 796,
        "didNotSolve": 76,
        "totalSubmitters": 1500,
        "url": "https://codingcompetitions.withgoogle.com/kickstart/round/0000000000201bfe/0000000000201c96"
    },
    {
        "year": 2017,
        "round": "E",
        "number": 3,
        "title": "Blackhole",
        "solvedTest2": 3,
        "solvedTest1": 1225,
        "didNotSolve": 22,
        "totalSubmitters": 1500,
        "url": "https://codingcompetitions.withgoogle.com/kickstart/round/0000000000201bfe/0000000000201b78"
    },
    {
        "year": 2017,
        "round": "D",
        "number": 1,
        "title": "Sightseeing",
        "solvedTest2": 563,
        "solvedTest1": 498,
        "didNotSolve": 1,
        "totalSubmitters": 1100,
        "url": "https://codingcompetitions.withgoogle.com/kickstart/round/0000000000201b77/0000000000201bfd"
    },
    {
        "year": 2017,
        "round": "D",
        "number": 2,
        "title": "Sherlock and Matrix Game",
        "solvedTest2": 15,
        "solvedTest1": 208,
        "didNotSolve": 273,
        "totalSubmitters": 1100,
        "url": "https://codingcompetitions.withgoogle.com/kickstart/round/0000000000201b77/0000000000201c95"
    },
    {
        "year": 2017,
        "round": "D",
        "number": 3,
        "title": "Trash",
        "solvedTest2": 9,
        "solvedTest1": 36,
        "didNotSolve": 44,
        "totalSubmitters": 1100,
        "url": "https://codingcompetitions.withgoogle.com/kickstart/round/0000000000201b77/0000000000201d23"
    },
    {
        "year": 2017,
        "round": "C",
        "number": 1,
        "title": "Ambiguous Cipher",
        "solvedTest2": 683,
        "solvedTest1": 130,
        "didNotSolve": 10,
        "totalSubmitters": 850,
        "url": "https://codingcompetitions.withgoogle.com/kickstart/round/0000000000201c98/0000000000201d26"
    },
    {
        "year": 2017,
        "round": "C",
        "number": 2,
        "title": "X Squared",
        "solvedTest2": 319,
        "solvedTest1": 58,
        "didNotSolve": 256,
        "totalSubmitters": 850,
        "url": "https://codingcompetitions.withgoogle.com/kickstart/round/0000000000201c98/0000000000201b7a"
    },
    {
        "year": 2017,
        "round": "C",
        "number": 3,
        "title": "Magical Thinking v2",
        "solvedTest2": 149,
        "solvedTest1": 421,
        "didNotSolve": 28,
        "totalSubmitters": 850,
        "url": "https://codingcompetitions.withgoogle.com/kickstart/round/0000000000201c98/0000000000201c00"
    },
    {
        "year": 2017,
        "round": "C",
        "number": 4,
        "title": "The 4M Corporation",
        "solvedTest2": 60,
        "solvedTest1": 49,
        "didNotSolve": 70,
        "totalSubmitters": 850,
        "url": "https://codingcompetitions.withgoogle.com/kickstart/round/0000000000201c98/0000000000201c99"
    },
    {
        "year": 2017,
        "round": "B",
        "number": 1,
        "title": "Math Encoder",
        "solvedTest2": 411,
        "solvedTest1": 409,
        "didNotSolve": 0,
        "totalSubmitters": 850,
        "url": "https://codingcompetitions.withgoogle.com/kickstart/round/0000000000201d27/0000000000201b7b"
    },
    {
        "year": 2017,
        "round": "B",
        "number": 2,
        "title": "Center",
        "solvedTest2": 97,
        "solvedTest1": 93,
        "didNotSolve": 234,
        "totalSubmitters": 850,
        "url": "https://codingcompetitions.withgoogle.com/kickstart/round/0000000000201d27/0000000000201c01"
    },
    {
        "year": 2017,
        "round": "B",
        "number": 3,
        "title": "Christmas Tree",
        "solvedTest2": 59,
        "solvedTest1": 383,
        "didNotSolve": 65,
        "totalSubmitters": 850,
        "url": "https://codingcompetitions.withgoogle.com/kickstart/round/0000000000201d27/0000000000201c9a"
    },
    {
        "year": 2017,
        "round": "A",
        "number": 1,
        "title": "Square Counting",
        "solvedTest2": 524,
        "solvedTest1": 899,
        "didNotSolve": 2,
        "totalSubmitters": 1500,
        "url": "https://codingcompetitions.withgoogle.com/kickstart/round/0000000000201c97/0000000000201d25"
    },
    {
        "year": 2017,
        "round": "A",
        "number": 2,
        "title": "Pattern Overlap",
        "solvedTest2": 287,
        "solvedTest1": 107,
        "didNotSolve": 387,
        "totalSubmitters": 1500,
        "url": "https://codingcompetitions.withgoogle.com/kickstart/round/0000000000201c97/0000000000201b79"
    },
    {
        "year": 2017,
        "round": "A",
        "number": 3,
        "title": "Two Cubes",
        "solvedTest2": 100,
        "solvedTest1": 152,
        "didNotSolve": 88,
        "totalSubmitters": 1500,
        "url": "https://codingcompetitions.withgoogle.com/kickstart/round/0000000000201c97/0000000000201bff"
    },
    {
        "year": 2016,
        "round": "E",
        "number": 1,
        "title": "Diwali lightings",
        "solvedTest2": 1262,
        "solvedTest1": 353,
        "didNotSolve": 65,
        "totalSubmitters": 1750,
        "url": "https://codingcompetitions.withgoogle.com/kickstart/round/0000000000201ca0/0000000000201d2f"
    },
    {
        "year": 2016,
        "round": "E",
        "number": 2,
        "title": "Beautiful Numbers",
        "solvedTest2": 211,
        "solvedTest1": 1218,
        "didNotSolve": 94,
        "totalSubmitters": 1750,
        "url": "https://codingcompetitions.withgoogle.com/kickstart/round/0000000000201ca0/0000000000201dba"
    },
    {
        "year": 2016,
        "round": "E",
        "number": 3,
        "title": "Partioning Number",
        "solvedTest2": 193,
        "solvedTest1": 453,
        "didNotSolve": 180,
        "totalSubmitters": 1750,
        "url": "https://codingcompetitions.withgoogle.com/kickstart/round/0000000000201ca0/0000000000201c08"
    },
    {
        "year": 2016,
        "round": "E",
        "number": 4,
        "title": "Sorting Array",
        "solvedTest2": 2,
        "solvedTest1": 3,
        "didNotSolve": 38,
        "totalSubmitters": 1750,
        "url": "https://codingcompetitions.withgoogle.com/kickstart/round/0000000000201ca0/0000000000201ca1"
    },
    {
        "year": 2016,
        "round": "D",
        "number": 1,
        "title": "Vote",
        "solvedTest2": 913,
        "solvedTest1": 447,
        "didNotSolve": 66,
        "totalSubmitters": 1550,
        "url": "https://codingcompetitions.withgoogle.com/kickstart/round/0000000000201db8/0000000000201c06"
    },
    {
        "year": 2016,
        "round": "D",
        "number": 2,
        "title": "Sitting",
        "solvedTest2": 305,
        "solvedTest1": 378,
        "didNotSolve": 367,
        "totalSubmitters": 1550,
        "url": "https://codingcompetitions.withgoogle.com/kickstart/round/0000000000201db8/0000000000201c9e"
    },
    {
        "year": 2016,
        "round": "D",
        "number": 3,
        "title": "Codejamon Cipher",
        "solvedTest2": 348,
        "solvedTest1": 305,
        "didNotSolve": 88,
        "totalSubmitters": 1550,
        "url": "https://codingcompetitions.withgoogle.com/kickstart/round/0000000000201db8/0000000000201d2e"
    },
    {
        "year": 2016,
        "round": "D",
        "number": 4,
        "title": "Stretch Rope",
        "solvedTest2": 36,
        "solvedTest1": 441,
        "didNotSolve": 67,
        "totalSubmitters": 1550,
        "url": "https://codingcompetitions.withgoogle.com/kickstart/round/0000000000201db8/0000000000201db9"
    },
    {
        "year": 2016,
        "round": "C",
        "number": 1,
        "title": "Monster Path",
        "solvedTest2": 655,
        "solvedTest1": 97,
        "didNotSolve": 154,
        "totalSubmitters": 1600,
        "url": "https://codingcompetitions.withgoogle.com/kickstart/round/0000000000201c0a/0000000000201ca4"
    },
    {
        "year": 2016,
        "round": "C",
        "number": 2,
        "title": "Safe Squares",
        "solvedTest2": 621,
        "solvedTest1": 839,
        "didNotSolve": 17,
        "totalSubmitters": 1600,
        "url": "https://codingcompetitions.withgoogle.com/kickstart/round/0000000000201c0a/0000000000201d31"
    },
    {
        "year": 2016,
        "round": "C",
        "number": 3,
        "title": "Evaluation",
        "solvedTest2": 552,
        "solvedTest1": 73,
        "didNotSolve": 218,
        "totalSubmitters": 1600,
        "url": "https://codingcompetitions.withgoogle.com/kickstart/round/0000000000201c0a/0000000000201dbc"
    },
    {
        "year": 2016,
        "round": "C",
        "number": 4,
        "title": "Soldiers",
        "solvedTest2": 24,
        "solvedTest1": 82,
        "didNotSolve": 80,
        "totalSubmitters": 1600,
        "url": "https://codingcompetitions.withgoogle.com/kickstart/round/0000000000201c0a/0000000000201c0b"
    },
    {
        "year": 2016,
        "round": "B",
        "number": 1,
        "title": "Sherlock and Parentheses",
        "solvedTest2": 2912,
        "solvedTest1": 934,
        "didNotSolve": 6,
        "totalSubmitters": 3900,
        "url": "https://codingcompetitions.withgoogle.com/kickstart/round/0000000000201c0c/0000000000201ca5"
    },
    {
        "year": 2016,
        "round": "B",
        "number": 2,
        "title": "Sherlock and Watson Gym Secrets",
        "solvedTest2": 268,
        "solvedTest1": 1492,
        "didNotSolve": 1251,
        "totalSubmitters": 3900,
        "url": "https://codingcompetitions.withgoogle.com/kickstart/round/0000000000201c0c/0000000000201d32"
    },
    {
        "year": 2016,
        "round": "B",
        "number": 3,
        "title": "Watson and Intervals",
        "solvedTest2": 152,
        "solvedTest1": 374,
        "didNotSolve": 670,
        "totalSubmitters": 3900,
        "url": "https://codingcompetitions.withgoogle.com/kickstart/round/0000000000201c0c/0000000000201dbd"
    },
    {
        "year": 2016,
        "round": "B",
        "number": 4,
        "title": "Sherlock and Permutation Sorting",
        "solvedTest2": 15,
        "solvedTest1": 29,
        "didNotSolve": 183,
        "totalSubmitters": 3900,
        "url": "https://codingcompetitions.withgoogle.com/kickstart/round/0000000000201c0c/0000000000201c0d"
    },
    {
        "year": 2016,
        "round": "A",
        "number": 1,
        "title": "Country Leader",
        "solvedTest2": 1722,
        "solvedTest1": 540,
        "didNotSolve": 25,
        "totalSubmitters": 2300,
        "url": "https://codingcompetitions.withgoogle.com/kickstart/round/0000000000201ca2/0000000000201d30"
    },
    {
        "year": 2016,
        "round": "A",
        "number": 2,
        "title": "Rain",
        "solvedTest2": 502,
        "solvedTest1": 56,
        "didNotSolve": 491,
        "totalSubmitters": 2300,
        "url": "https://codingcompetitions.withgoogle.com/kickstart/round/0000000000201ca2/0000000000201dbb"
    },
    {
        "year": 2016,
        "round": "A",
        "number": 3,
        "title": "Jane's Flower Shop",
        "solvedTest2": 319,
        "solvedTest1": 684,
        "didNotSolve": 261,
        "totalSubmitters": 2300,
        "url": "https://codingcompetitions.withgoogle.com/kickstart/round/0000000000201ca2/0000000000201c09"
    },
    {
        "year": 2016,
        "round": "A",
        "number": 4,
        "title": "Clash Royale",
        "solvedTest2": 28,
        "solvedTest1": 172,
        "didNotSolve": 93,
        "totalSubmitters": 2300,
        "url": "https://codingcompetitions.withgoogle.com/kickstart/round/0000000000201ca2/0000000000201ca3"
    }
]